[
  {
    "key": "sidarto2021halal",
    "doi": "10.3389/fbloc.2021.612898",
    "status": "OK",
    "title": "Improving Halal Traceability Process in the Poultry Industry Utilizing Blockchain Technology: Use Case in Indonesia",
    "year": 2021,
    "authors": "Sidarto, Hamka"
  },
  {
    "key": "alourani2025halal",
    "doi": "10.63332/joph.v5i2.437",
    "status": "OK",
    "title": "Halal Food Traceability System using AI and Blockchain",
    "year": 2025,
    "authors": "Alourani, Khan"
  },
  {
    "key": "marianingsih2024halal",
    "doi": "10.53515/lt.v7i2.165",
    "status": "OK",
    "title": "Ai–Blockchain-Enabled Halal Traceability for Cross-Border Certification Harmonization: A Framework for Digital Halal Assurance",
    "year": 2026,
    "authors": "Marianingsih"
  },
  {
    "key": "rejeb2018halal",
    "doi": "10.14513/actatechjaur.v11.n4.467",
    "status": "OK",
    "title": "Halal Meat Supply Chain Traceability based on HACCP, Blockchain and Internet of Things",
    "year": 2018,
    "authors": "Rejeb"
  },
  {
    "key": "rashid2018halal",
    "doi": "10.18488/journal.1.2018.88.569.579",
    "status": "OK",
    "title": "Relationship between Halal Traceability System Adoptions on Halal Food Supply Chain Integrity and Performance",
    "year": 2018,
    "authors": "Rashid, Supian"
  },
  {
    "key": "casino2021systematic",
    "doi": "10.1016/j.tele.2018.11.006",
    "status": "OK",
    "title": "A systematic literature review of blockchain-based applications: Current status, classification and open issues",
    "year": 2019,
    "authors": "Casino, Dasaklis"
  },
  {
    "key": "kamilaris2019blockchain",
    "doi": "10.1016/j.tifs.2019.07.034",
    "status": "OK",
    "title": "The rise of blockchain technology in agriculture and food supply chains",
    "year": 2019,
    "authors": "Kamilaris, Fonts"
  },
  {
    "key": "rejeb2020blockchain",
    "doi": "10.3390/logistics4040027",
    "status": "OK",
    "title": "Blockchain Technology in the Food Industry: A Review of Potentials, Challenges and Future Research Directions",
    "year": 2020,
    "authors": "Rejeb, Keogh"
  },
  {
    "key": "kamath2018blockchain",
    "doi": "10.31585/jbba-1-1-(10)2018",
    "status": "OK",
    "title": "Food Traceability on Blockchain: Walmart’s Pork and Mango Pilots with IBM",
    "year": 2018,
    "authors": "Kamath"
  },
  {
    "key": "zheng2020overview",
    "doi": "10.1016/j.future.2019.12.019",
    "status": "OK",
    "title": "An overview on smart contracts: Challenges, advances and platforms",
    "year": 2020,
    "authors": "Zheng, Xie"
  },
  {
    "key": "andoni2019blockchain",
    "doi": "10.1016/j.rser.2018.10.014",
    "status": "OK",
    "title": "Blockchain technology in the energy sector: A systematic review of challenges and opportunities",
    "year": 2019,
    "authors": "Andoni, Robu"
  },
  {
    "key": "kouhizadeh2018blockchain",
    "doi": "10.3390/su10103652",
    "status": "OK",
    "title": "Blockchain Practices, Potentials, and Perspectives in Greening Supply Chains",
    "year": 2018,
    "authors": "Kouhizadeh, Sarkis"
  },
  {
    "key": "friedman2017value",
    "doi": "10.7551/mitpress/7585.001.0001",
    "status": "OK",
    "title": "Value Sensitive Design",
    "year": 2019,
    "authors": "Friedman, Hendry"
  },
  {
    "key": "christidis2016blockchain",
    "doi": "10.1109/ACCESS.2016.2566339",
    "status": "OK",
    "title": "Blockchains and Smart Contracts for the Internet of Things",
    "year": 2016,
    "authors": "Christidis, Devetsikiotis"
  },
  {
    "key": "kshetri2018blockchain",
    "doi": "10.1016/j.ijinfomgt.2017.12.005",
    "status": "OK",
    "title": "1 Blockchain’s roles in meeting key supply chain management objectives",
    "year": 2018,
    "authors": "Kshetri"
  },
  {
    "key": "galvez2018future",
    "doi": "10.1016/j.trac.2018.08.011",
    "status": "OK",
    "title": "Future challenges on the use of blockchain for food traceability analysis",
    "year": 2018,
    "authors": "Galvez, Mejuto"
  },
  {
    "key": "abeyratne2016blockchain",
    "doi": "10.15623/ijret.2016.0509001",
    "status": "OK",
    "title": "BLOCKCHAIN READY MANUFACTURING SUPPLY CHAIN USING DISTRIBUTED LEDGER",
    "year": 2016,
    "authors": "."
  },
  {
    "key": "viriyasitavat2019blockchain",
    "doi": "10.1016/j.jii.2018.07.004",
    "status": "OK",
    "title": "Blockchain characteristics and consensus in modern business processes",
    "year": 2019,
    "authors": "Viriyasitavat, Hoonsopon"
  },
  {
    "key": "caro2018blockchain",
    "doi": "10.1109/iot-tuscany.2018.8373021",
    "status": "OK",
    "title": "Blockchain-based traceability in Agri-Food supply chain management: A practical implementation",
    "year": 2018,
    "authors": "Caro, Ali"
  },
  {
    "key": "underwood2016blockchain",
    "doi": "10.1145/2994581",
    "status": "OK",
    "title": "Blockchain beyond bitcoin",
    "year": 2016,
    "authors": "Underwood"
  }
]